playbook/__init__.py
playbook/functions.py
playbook/cli/__init__.py
playbook/cli/common.py
playbook/cli/error_handler.py
playbook/cli/main.py
playbook/cli/commands/__init__.py
playbook/cli/commands/config.py
playbook/cli/commands/create.py
playbook/cli/commands/info.py
playbook/cli/commands/run.py
playbook/cli/commands/set_status.py
playbook/cli/commands/show.py
playbook/cli/commands/validate.py
playbook/cli/commands/version.py
playbook/cli/commands/view_dag.py
playbook/cli/interaction/__init__.py
playbook/cli/interaction/handlers.py
playbook/cli/output/__init__.py
playbook/config/__init__.py
playbook/config/manager.py
playbook/domain/__init__.py
playbook/domain/exceptions.py
playbook/domain/models.py
playbook/domain/plugins.py
playbook/domain/ports.py
playbook/infrastructure/__init__.py
playbook/infrastructure/conditions.py
playbook/infrastructure/parser.py
playbook/infrastructure/persistence.py
playbook/infrastructure/plugin_registry.py
playbook/infrastructure/process.py
playbook/infrastructure/statistics.py
playbook/infrastructure/variables.py
playbook/infrastructure/visualization.py
playbook/infrastructure/plugins/__init__.py
playbook/infrastructure/plugins/python_plugin.py
playbook/service/__init__.py
playbook/service/engine.py
playbook/service/statistics.py
playbook-1.3.1.dist-info/licenses/LICENSE
playbook-1.3.1.dist-info/METADATA
playbook-1.3.1.dist-info/WHEEL
playbook-1.3.1.dist-info/entry_points.txt
playbook-1.3.1.dist-info/top_level.txt
playbook-1.3.1.dist-info/RECORD
