Metadata-Version: 2.4
Name: playbook
Version: 1.3.1
Summary: A workflow engine for operations
Author-email: sysid <sysid@gmx.de>
Project-URL: Homepage, https://github.com/sysid/playbook
Project-URL: Bug Tracker, https://github.com/sysid/playbook/issues
Classifier: Programming Language :: Python :: 3
Classifier: Operating System :: OS Independent
Requires-Python: >=3.13
License-File: LICENSE
Requires-Dist: graphviz>=0.20.3
Requires-Dist: importlib-metadata>=8.7.0
Requires-Dist: jinja2>=3.1.0
Requires-Dist: pydantic>=2.11.4
Requires-Dist: pyyaml>=6.0.0
Requires-Dist: rich>=14.0.0
Requires-Dist: typer>=0.15.3
Requires-Dist: click==8.1.8
Dynamic: license-file
